BaShijianDangzuoPengyou/README.md
BaShijianDangzuoPengyou/__init__.py
BaShijianDangzuoPengyou/__main__.py
BaShijianDangzuoPengyou/file.epub
BaShijianDangzuoPengyou/index.html
BaShijianDangzuoPengyou/css/__init__.py
BaShijianDangzuoPengyou/css/annotations.css
BaShijianDangzuoPengyou/css/main.css
BaShijianDangzuoPengyou/css/normalize.css
BaShijianDangzuoPengyou/css/popup.css
BaShijianDangzuoPengyou/font/__init__.py
BaShijianDangzuoPengyou/font/fontello.eot
BaShijianDangzuoPengyou/font/fontello.svg
BaShijianDangzuoPengyou/font/fontello.ttf
BaShijianDangzuoPengyou/font/fontello.woff
BaShijianDangzuoPengyou/img/__init__.py
BaShijianDangzuoPengyou/img/annotator-glyph-sprite.png
BaShijianDangzuoPengyou/img/annotator-icon-sprite.png
BaShijianDangzuoPengyou/img/apple-touch-icon.png
BaShijianDangzuoPengyou/img/cancelfullscreen.png
BaShijianDangzuoPengyou/img/close.png
BaShijianDangzuoPengyou/img/fullscreen.png
BaShijianDangzuoPengyou/img/loader.gif
BaShijianDangzuoPengyou/img/menu-icon.png
BaShijianDangzuoPengyou/img/save.png
BaShijianDangzuoPengyou/img/saved.png
BaShijianDangzuoPengyou/img/settings-s.png
BaShijianDangzuoPengyou/img/settings.png
BaShijianDangzuoPengyou/img/star.png
BaShijianDangzuoPengyou/js/__init__.py
BaShijianDangzuoPengyou/js/epub.js
BaShijianDangzuoPengyou/js/epub.min.js
BaShijianDangzuoPengyou/js/epub.min.map
BaShijianDangzuoPengyou/js/hooks.min.js
BaShijianDangzuoPengyou/js/hooks.min.map
BaShijianDangzuoPengyou/js/reader.js
BaShijianDangzuoPengyou/js/reader.js.map
BaShijianDangzuoPengyou/js/reader.min.js
BaShijianDangzuoPengyou/js/reader.min.map
BaShijianDangzuoPengyou/js/hooks/__init__.py
BaShijianDangzuoPengyou/js/hooks/extensions/__init__.py
BaShijianDangzuoPengyou/js/hooks/extensions/highlight.js
BaShijianDangzuoPengyou/js/libs/__init__.py
BaShijianDangzuoPengyou/js/libs/jquery.min.js
BaShijianDangzuoPengyou/js/libs/localforage.min.js
BaShijianDangzuoPengyou/js/libs/screenfull.js
BaShijianDangzuoPengyou/js/libs/screenfull.min.js
ba_shijian_dangzuo_pengyou-2024.3.4.0.dist-info/METADATA
ba_shijian_dangzuo_pengyou-2024.3.4.0.dist-info/WHEEL
ba_shijian_dangzuo_pengyou-2024.3.4.0.dist-info/entry_points.txt
ba_shijian_dangzuo_pengyou-2024.3.4.0.dist-info/top_level.txt
ba_shijian_dangzuo_pengyou-2024.3.4.0.dist-info/RECORD
